<?xml version="1.0" encoding="UTF-8"?>
<root>
  <row>
    <patient id>DP001</patient id>
    <patient name>Vikram</patient name>
    <phone number>9084567643</phone number>
    <age>30</age>
    <address>New jersey</address>
  </row>
  <row>
    <patient id>DP002</patient id>
    <patient name>Stephen</patient name>
    <phone number>6783251890</phone number>
    <age>27</age>
    <address>New jersey</address>
  </row>
  <row>
    <patient id>DP003</patient id>
    <patient name>Ronald</patient name>
    <phone number>546439335</phone number>
    <age>22</age>
    <address>Newark</address>
  </row>
  <row>
    <patient id>DP004</patient id>
    <patient name>Suzy</patient name>
    <phone number>437999217</phone number>
    <age>32</age>
    <address>New jersey</address>
  </row>
  <row>
    <patient id>DP005</patient id>
    <patient name>Thimothy</patient name>
    <phone number>543232888</phone number>
    <age>25</age>
    <address>New jersey</address>
  </row>
  <row>
    <patient id>DP006</patient id>
    <patient name>Rose</patient name>
    <phone number>549278460</phone number>
    <age>24</age>
    <address>Trenton</address>
  </row>
  <row>
    <patient id>DP007</patient id>
    <patient name>Francis</patient name>
    <phone number>589207067</phone number>
    <age>29</age>
    <address>New jersey</address>
  </row>
  <row>
    <patient id>DP008</patient id>
    <patient name>Glory</patient name>
    <phone number>823486289</phone number>
    <age>25</age>
    <address>New jersey</address>
  </row>
  <row>
    <patient id>DP009</patient id>
    <patient name>Rajesh</patient name>
    <phone number>105776551</phone number>
    <age>30</age>
    <address>Jersey city</address>
  </row>
  <row>
    <patient id>DP010</patient id>
    <patient name>Heniz</patient name>
    <phone number>129204473</phone number>
    <age>24</age>
    <address>New jersey</address>
  </row>
</root>